{
    "result"  : "success",
    "data"    : [
        {"id": 1,"user":"刘德华","numb":"10015","depart":"商务部","date":"2019-08-20 09:00 至 2019-08-20 18:30","duration":"8.5小时","type":"工作日加班","offset":"调休"},
        {"id": 2,"user":"刘德华","numb":"10015","depart":"商务部","date":"2019-08-20 09:00 至 2019-08-20 18:30","duration":"8.5小时","type":"休息日加班","offset":"调休"},
        {"id": 3,"user":"刘德华","numb":"10015","depart":"商务部","date":"2019-08-20 09:00 至 2019-08-20 18:30","duration":"8.5小时","type":"节假日加班","offset":"调休"},
        {"id": 4,"user":"刘德华","numb":"10015","depart":"商务部","date":"2019-08-20 09:00 至 2019-08-20 18:30","duration":"8.5小时","type":"休息日加班","offset":"调休"},
        {"id": 5,"user":"刘德华","numb":"10015","depart":"商务部","date":"2019-08-20 09:00 至 2019-08-20 18:30","duration":"8.5小时","type":"休息日加班","offset":"调休"},
        {"id": 6,"user":"刘德华","numb":"10015","depart":"商务部","date":"2019-08-20 09:00 至 2019-08-20 18:30","duration":"8.5小时","type":"休息日加班","offset":"调休"},
        {"id": 7,"user":"刘德华","numb":"10015","depart":"商务部","date":"2019-08-20 09:00 至 2019-08-20 18:30","duration":"8.5小时","type":"休息日加班","offset":"调休"},
        {"id": 8,"user":"刘德华","numb":"10015","depart":"商务部","date":"2019-08-20 09:00 至 2019-08-20 18:30","duration":"8.5小时","type":"休息日加班","offset":"调休"},
        {"id": 9,"user":"刘德华","numb":"10015","depart":"商务部","date":"2019-08-20 09:00 至 2019-08-20 18:30","duration":"8.5小时","type":"休息日加班","offset":"调休"},
        {"id":10,"user":"刘德华","numb":"10015","depart":"商务部","date":"2019-08-20 09:00 至 2019-08-20 18:30","duration":"8.5小时","type":"休息日加班","offset":"调休"},
        {"id":11,"user":"刘德华","numb":"10015","depart":"商务部","date":"2019-08-20 09:00 至 2019-08-20 18:30","duration":"8.5小时","type":"休息日加班","offset":"调休"},
        {"id":12,"user":"刘德华","numb":"10015","depart":"商务部","date":"2019-08-20 09:00 至 2019-08-20 18:30","duration":"8.5小时","type":"休息日加班","offset":"调休"},                            
        {"id":13,"user":"刘德华","numb":"10015","depart":"商务部","date":"2019-08-20 09:00 至 2019-08-20 18:30","duration":"8.5小时","type":"休息日加班","offset":"调休"},
        {"id":14,"user":"刘德华","numb":"10015","depart":"商务部","date":"2019-08-20 09:00 至 2019-08-20 18:30","duration":"8.5小时","type":"休息日加班","offset":"调休"},
        {"id":15,"user":"刘德华","numb":"10015","depart":"商务部","date":"2019-08-20 09:00 至 2019-08-20 18:30","duration":"8.5小时","type":"休息日加班","offset":"调休"},
        {"id":16,"user":"刘德华","numb":"10015","depart":"商务部","date":"2019-08-20 09:00 至 2019-08-20 18:30","duration":"8.5小时","type":"休息日加班","offset":"调休"},
        {"id":17,"user":"刘德华","numb":"10015","depart":"商务部","date":"2019-08-20 09:00 至 2019-08-20 18:30","duration":"8.5小时","type":"休息日加班","offset":"调休"},
        {"id":18,"user":"刘德华","numb":"10015","depart":"商务部","date":"2019-08-20 09:00 至 2019-08-20 18:30","duration":"8.5小时","type":"休息日加班","offset":"调休"},
        {"id":19,"user":"刘德华","numb":"10015","depart":"商务部","date":"2019-08-20 09:00 至 2019-08-20 18:30","duration":"8.5小时","type":"休息日加班","offset":"调休"},
        {"id":20,"user":"刘德华","numb":"10015","depart":"商务部","date":"2019-08-20 09:00 至 2019-08-20 18:30","duration":"8.5小时","type":"休息日加班","offset":"调休"}
    ],
    "message" : "",
    "pager"   : {"page":1,"recTotal":20,"recPerPage":20}
}